zboxapi/__init__.py
zboxapi/dns.py
zboxapi/main.py
zboxapi/vlan.py
zboxapi-0.0.7.dist-info/METADATA
zboxapi-0.0.7.dist-info/WHEEL
zboxapi-0.0.7.dist-info/entry_points.txt
zboxapi-0.0.7.dist-info/RECORD
