Metadata-Version: 2.1
Name: zboxapi
Version: 0.0.7
Summary: 
Author: Kelby Valenti
Author-email: kelby.valenti@gmail.com
Requires-Python: >=3.10
Classifier: Programming Language :: Python :: 3
Classifier: Programming Language :: Python :: 3.10
Classifier: Programming Language :: Python :: 3.11
Classifier: Programming Language :: Python :: 3.12
Requires-Dist: fastapi (==0.111.0)
Requires-Dist: ipython (>=8.24.0,<9.0.0)
Requires-Dist: uvicorn (==0.29.0)
